tamilan/__init__.py
tamilan/chatbot.py
tamilan/functions.py
tamilan/twosum.py
tamilan-0.1.9.dist-info/METADATA
tamilan-0.1.9.dist-info/WHEEL
tamilan-0.1.9.dist-info/top_level.txt
tamilan-0.1.9.dist-info/RECORD
